deep_image_matching/__init__.py
deep_image_matching/config.py
deep_image_matching/constants.py
deep_image_matching/graph.py
deep_image_matching/gui.py
deep_image_matching/image_matching.py
deep_image_matching/image_retrieval.py
deep_image_matching/low_resolution.py
deep_image_matching/openmvg_reconstruction.py
deep_image_matching/pairs_generator.py
deep_image_matching/parser.py
deep_image_matching/reconstruction.py
deep_image_matching/triangulation.py
deep_image_matching/visualization.py
deep_image_matching/extractors/__init__.py
deep_image_matching/extractors/alike.py
deep_image_matching/extractors/aliked.py
deep_image_matching/extractors/cosplace.py
deep_image_matching/extractors/dedode.py
deep_image_matching/extractors/disk.py
deep_image_matching/extractors/extractor_base.py
deep_image_matching/extractors/keynetaffnethardnet.py
deep_image_matching/extractors/kornia_features.py
deep_image_matching/extractors/netvlad.py
deep_image_matching/extractors/no_extractor.py
deep_image_matching/extractors/openibl.py
deep_image_matching/extractors/orb.py
deep_image_matching/extractors/sift.py
deep_image_matching/extractors/superpoint.py
deep_image_matching/io/__init__.py
deep_image_matching/io/colmap_read_write_model.py
deep_image_matching/io/h5.py
deep_image_matching/io/h5_to_db.py
deep_image_matching/io/h5_to_micmac.py
deep_image_matching/io/h5_to_openmvg.py
deep_image_matching/io/micmac_to_h5.py
deep_image_matching/matchers/__init__.py
deep_image_matching/matchers/adalam.py
deep_image_matching/matchers/kornia_matcher.py
deep_image_matching/matchers/lightglue.py
deep_image_matching/matchers/loftr.py
deep_image_matching/matchers/matcher_base.py
deep_image_matching/matchers/roma.py
deep_image_matching/matchers/se2loftr.py
deep_image_matching/matchers/superglue.py
deep_image_matching/thirdparty/__init__.py
deep_image_matching/thirdparty/transformations.py
deep_image_matching/thirdparty/ALIKED/count_flops.py
deep_image_matching/thirdparty/ALIKED/demo_pair.py
deep_image_matching-1.2.4.dist-info/LICENSE
deep_image_matching-1.2.4.dist-info/METADATA
deep_image_matching-1.2.4.dist-info/WHEEL
deep_image_matching-1.2.4.dist-info/top_level.txt
deep_image_matching-1.2.4.dist-info/RECORD
