Metadata-Version: 2.1
Name: deep_image_matching
Version: 1.2.4
Summary: Multiview matching with deep-learning and hand-crafted local features for COLMAP and other SfM software.
Author-email: Francesco Ioli <francesco.ioli@polimi.it>, Luca Morelli <lmorelli@fbk.eu>
License: # LICENSE
Project-URL: Homepage, https://github.com/3DOM-FBK/deep-image-matching
Project-URL: Documentation, https://3dom-fbk.github.io/deep-image-matching/
Project-URL: Download, https://github.com/3DOM-FBK/deep-image-matching
Project-URL: Source Code, https://github.com/3DOM-FBK/deep-image-matching
Keywords: image-matching,deep-learning,local-features,multiview-matching,sfm
Classifier: Programming Language :: Python
Classifier: Programming Language :: Python :: 3
Requires-Python: >=3.8
License-File: LICENSE
Requires-Dist: numpy
Requires-Dist: scipy
Requires-Dist: matplotlib
Requires-Dist: torch
Requires-Dist: torchvision
Requires-Dist: pillow
Requires-Dist: opencv-python
Requires-Dist: opencv-contrib-python
Requires-Dist: pydegensac
Requires-Dist: kornia >=0.7.2
Requires-Dist: h5py
Requires-Dist: tqdm
Requires-Dist: exifread
Requires-Dist: joblib
Requires-Dist: pyyaml
Requires-Dist: packaging
Requires-Dist: einops
Requires-Dist: pyvis >=0.3.2
Requires-Dist: yacs >=0.1.8
Requires-Dist: e2cnn
Requires-Dist: pytorch-lightning
Requires-Dist: pytest
Provides-Extra: dev
Requires-Dist: flake8 ; extra == 'dev'
Requires-Dist: black ; extra == 'dev'
Requires-Dist: bumpver ; extra == 'dev'
Requires-Dist: isort ; extra == 'dev'
Requires-Dist: pip-tools ; extra == 'dev'
Requires-Dist: pytest ; extra == 'dev'
Requires-Dist: mkdocs ; extra == 'dev'
Requires-Dist: mkdocs-material ; extra == 'dev'
Requires-Dist: mkdocstrings[python] ; extra == 'dev'
Requires-Dist: pre-commit ; extra == 'dev'
